pypinindia/All_India_pincode_data.csv
pypinindia/__init__.py
pypinindia/batch.py
pypinindia/cli.py
pypinindia/core.py
pypinindia/exceptions.py
pypinindia/main.py
pypinindia/test.py
pypinindia/util.py
pypinindia-0.1.15.dist-info/licenses/LICENSE
pypinindia-0.1.15.dist-info/METADATA
pypinindia-0.1.15.dist-info/WHEEL
pypinindia-0.1.15.dist-info/entry_points.txt
pypinindia-0.1.15.dist-info/top_level.txt
pypinindia-0.1.15.dist-info/RECORD
