Metadata-Version: 2.4
Name: pypinindia
Version: 0.1.15
Summary: Indian Pincodes and related Information with modern Python library structure
Author-email: Raja CSP Raman <raja.csp@gmail.com>, Meeran Ashfaaq <meeran231422@gmail.com>
License: Apache-2.0
Project-URL: Homepage, https://github.com/kactlabs/pypinindia
Project-URL: Repository, https://github.com/kactlabs/pypinindia
Project-URL: Issues, https://github.com/kactlabs/pypinindia/issues
Project-URL: Documentation, https://pypinindia.readthedocs.io
Project-URL: Source, https://github.com/kactlabs/pypinindia
Keywords: pincode,india,postal,zip,location,geography
Classifier: Development Status :: 4 - Beta
Classifier: Intended Audience :: Developers
Classifier: License :: OSI Approved :: Apache Software License
Classifier: Operating System :: OS Independent
Classifier: Programming Language :: Python :: 3
Classifier: Programming Language :: Python :: 3.8
Classifier: Programming Language :: Python :: 3.9
Classifier: Programming Language :: Python :: 3.10
Classifier: Programming Language :: Python :: 3.11
Classifier: Programming Language :: Python :: 3.12
Classifier: Topic :: Software Development :: Libraries :: Python Modules
Classifier: Topic :: Scientific/Engineering :: GIS
Classifier: Topic :: Database
Requires-Python: >=3.8
License-File: LICENSE
Requires-Dist: pandas>=1.0.0
Provides-Extra: dev
Requires-Dist: pytest>=7.0.0; extra == "dev"
Requires-Dist: pytest-cov>=4.0.0; extra == "dev"
Requires-Dist: black>=22.0.0; extra == "dev"
Requires-Dist: flake8>=5.0.0; extra == "dev"
Requires-Dist: mypy>=1.0.0; extra == "dev"
Dynamic: license-file
